[
  {
    "期号": "26076",
    "开奖日期": "2026-07-08",
    "前区": "15,20,27,28,35",
    "后区": "02,11",
    "前区号码1": "15",
    "前区号码2": "20",
    "前区号码3": "27",
    "前区号码4": "28",
    "前区号码5": "35",
    "后区号码1": "02",
    "后区号码2": "11",
    "总销售额": "303,115,587",
    "奖池余额": "804,904,836.99"
  },
  {
    "期号": "26077",
    "开奖日期": "2026-07-11",
    "前区": "04,14,19,24,27",
    "后区": "06,07",
    "前区号码1": "04",
    "前区号码2": "14",
    "前区号码3": "19",
    "前区号码4": "24",
    "前区号码5": "27",
    "后区号码1": "06",
    "后区号码2": "07",
    "总销售额": "318,922,356",
    "奖池余额": "797,164,073.48"
  },
  {
    "期号": "26078",
    "开奖日期": "2026-07-13",
    "前区": "02,13,20,25,32",
    "后区": "08,11",
    "前区号码1": "02",
    "前区号码2": "13",
    "前区号码3": "20",
    "前区号码4": "25",
    "前区号码5": "32",
    "后区号码1": "08",
    "后区号码2": "11",
    "总销售额": "302,935,941",
    "奖池余额": "818,797,138.41"
  },
  {
    "期号": "26079",
    "开奖日期": "2026-07-15",
    "前区": "06,08,23,26,27",
    "后区": "05,12",
    "前区号码1": "06",
    "前区号码2": "08",
    "前区号码3": "23",
    "前区号码4": "26",
    "前区号码5": "27",
    "后区号码1": "05",
    "后区号码2": "12",
    "总销售额": "301,975,334",
    "奖池余额": "794,651,243.34"
  },
  {
    "期号": "26080",
    "开奖日期": "2026-07-18",
    "前区": "05,10,15,21,23",
    "后区": "07,08",
    "前区号码1": "05",
    "前区号码2": "10",
    "前区号码3": "15",
    "前区号码4": "21",
    "前区号码5": "23",
    "后区号码1": "07",
    "后区号码2": "08",
    "总销售额": "325,550,165",
    "奖池余额": "765,513,154.43"
  }
]