[
  {
    "期号": "26047",
    "开奖日期": "2026-04-28",
    "红球": "07,16,21,24,27,30",
    "蓝球": "07",
    "红球号码1": "07",
    "红球号码2": "16",
    "红球号码3": "21",
    "红球号码4": "24",
    "红球号码5": "27",
    "红球号码6": "30",
    "蓝球号码1": "07",
    "总销售额": "1,505,111,504",
    "奖池余额": "383,992,530"
  },
  {
    "期号": "26048",
    "开奖日期": "2026-04-30",
    "红球": "09,15,18,24,28,33",
    "蓝球": "01",
    "红球号码1": "09",
    "红球号码2": "15",
    "红球号码3": "18",
    "红球号码4": "24",
    "红球号码5": "28",
    "红球号码6": "33",
    "蓝球号码1": "01",
    "总销售额": "1,520,262,206",
    "奖池余额": "381,163,108"
  },
  {
    "期号": "26049",
    "开奖日期": "2026-05-03",
    "红球": "03,04,14,15,18,20",
    "蓝球": "02",
    "红球号码1": "03",
    "红球号码2": "04",
    "红球号码3": "14",
    "红球号码4": "15",
    "红球号码5": "18",
    "红球号码6": "20",
    "蓝球号码1": "02",
    "总销售额": "1,490,262,206",
    "奖池余额": "378,548,054"
  },
  {
    "期号": "26050",
    "开奖日期": "2026-05-05",
    "红球": "06,09,25,27,28,30",
    "蓝球": "03",
    "红球号码1": "06",
    "红球号码2": "09",
    "红球号码3": "25",
    "红球号码4": "27",
    "红球号码5": "28",
    "红球号码6": "30",
    "蓝球号码1": "03",
    "总销售额": "1,470,262,206",
    "奖池余额": "368,215,788"
  },
  {
    "期号": "26051",
    "开奖日期": "2026-05-07",
    "红球": "09,14,15,16,29,30",
    "蓝球": "10",
    "红球号码1": "09",
    "红球号码2": "14",
    "红球号码3": "15",
    "红球号码4": "16",
    "红球号码5": "29",
    "红球号码6": "30",
    "蓝球号码1": "10",
    "总销售额": "1,400,262,206",
    "奖池余额": "386,809,756"
  },
  {
    "期号": "26052",
    "开奖日期": "2026-05-10",
    "红球": "01,03,11,22,26,31",
    "蓝球": "11",
    "红球号码1": "01",
    "红球号码2": "03",
    "红球号码3": "11",
    "红球号码4": "22",
    "红球号码5": "26",
    "红球号码6": "31",
    "蓝球号码1": "11",
    "总销售额": "1,306,883,761",
    "奖池余额": "417,267,288"
  },
  {
    "期号": "26053",
    "开奖日期": "2026-05-12",
    "红球": "01,02,03,08,13,14",
    "蓝球": "02",
    "红球号码1": "01",
    "红球号码2": "02",
    "红球号码3": "03",
    "红球号码4": "08",
    "红球号码5": "13",
    "红球号码6": "14",
    "蓝球号码1": "02",
    "总销售额": "1,276,883,761",
    "奖池余额": "395,029,142"
  },
  {
    "期号": "26054",
    "开奖日期": "2026-05-14",
    "红球": "13,20,25,29,30,33",
    "蓝球": "02",
    "红球号码1": "13",
    "红球号码2": "20",
    "红球号码3": "25",
    "红球号码4": "29",
    "红球号码5": "30",
    "红球号码6": "33",
    "蓝球号码1": "02",
    "总销售额": "1,251,883,761",
    "奖池余额": "391,858,874"
  },
  {
    "期号": "26055",
    "开奖日期": "2026-05-17",
    "红球": "04,11,24,25,32,33",
    "蓝球": "13",
    "红球号码1": "04",
    "红球号码2": "11",
    "红球号码3": "24",
    "红球号码4": "25",
    "红球号码5": "32",
    "红球号码6": "33",
    "蓝球号码1": "13",
    "总销售额": "1,237,107,160",
    "奖池余额": "422,769,486"
  },
  {
    "期号": "26056",
    "开奖日期": "2026-05-19",
    "红球": "10,19,21,22,31,33",
    "蓝球": "05",
    "红球号码1": "10",
    "红球号码2": "19",
    "红球号码3": "21",
    "红球号码4": "22",
    "红球号码5": "31",
    "红球号码6": "33",
    "蓝球号码1": "05",
    "总销售额": "1,229,771,516",
    "奖池余额": "391,304,582"
  },
  {
    "期号": "26057",
    "开奖日期": "2026-05-21",
    "红球": "01,10,22,24,28,30",
    "蓝球": "07",
    "红球号码1": "01",
    "红球号码2": "10",
    "红球号码3": "22",
    "红球号码4": "24",
    "红球号码5": "28",
    "红球号码6": "30",
    "蓝球号码1": "07",
    "总销售额": "1,199,771,516",
    "奖池余额": "397,400,020"
  },
  {
    "期号": "26058",
    "开奖日期": "2026-05-24",
    "红球": "01,04,07,21,29,30",
    "蓝球": "01",
    "红球号码1": "01",
    "红球号码2": "04",
    "红球号码3": "07",
    "红球号码4": "21",
    "红球号码5": "29",
    "红球号码6": "30",
    "蓝球号码1": "01",
    "总销售额": "1,154,771,516",
    "奖池余额": "425,121,686"
  },
  {
    "期号": "26059",
    "开奖日期": "2026-05-26",
    "红球": "08,16,26,28,29,30",
    "蓝球": "15",
    "红球号码1": "08",
    "红球号码2": "16",
    "红球号码3": "26",
    "红球号码4": "28",
    "红球号码5": "29",
    "红球号码6": "30",
    "蓝球号码1": "15",
    "总销售额": "1,139,990,273",
    "奖池余额": "392,773,558"
  },
  {
    "期号": "26060",
    "开奖日期": "2026-05-28",
    "红球": "07,09,10,16,22,27",
    "蓝球": "11",
    "红球号码1": "07",
    "红球号码2": "09",
    "红球号码3": "10",
    "红球号码4": "16",
    "红球号码5": "22",
    "红球号码6": "27",
    "蓝球号码1": "11",
    "总销售额": "1,049,990,273",
    "奖池余额": "398,771,788"
  },
  {
    "期号": "26061",
    "开奖日期": "2026-05-31",
    "红球": "01,04,05,15,23,28",
    "蓝球": "07",
    "红球号码1": "01",
    "红球号码2": "04",
    "红球号码3": "05",
    "红球号码4": "15",
    "红球号码5": "23",
    "红球号码6": "28",
    "蓝球号码1": "07",
    "总销售额": "1,009,990,273",
    "奖池余额": "429,422,172"
  },
  {
    "期号": "26062",
    "开奖日期": "2026-06-02",
    "红球": "02,04,07,14,28,29",
    "蓝球": "09",
    "红球号码1": "02",
    "红球号码2": "04",
    "红球号码3": "07",
    "红球号码4": "14",
    "红球号码5": "28",
    "红球号码6": "29",
    "蓝球号码1": "09",
    "总销售额": "909,990,283",
    "奖池余额": "402,189,304"
  },
  {
    "期号": "26063",
    "开奖日期": "2026-06-04",
    "红球": "02,08,25,28,30,31",
    "蓝球": "02",
    "红球号码1": "02",
    "红球号码2": "08",
    "红球号码3": "25",
    "红球号码4": "28",
    "红球号码5": "30",
    "红球号码6": "31",
    "蓝球号码1": "02",
    "总销售额": "816,837,950",
    "奖池余额": "393,294,950"
  },
  {
    "期号": "26064",
    "开奖日期": "2026-06-07",
    "红球": "01,09,15,18,29,33",
    "蓝球": "15",
    "红球号码1": "01",
    "红球号码2": "09",
    "红球号码3": "15",
    "红球号码4": "18",
    "红球号码5": "29",
    "红球号码6": "33",
    "蓝球号码1": "15",
    "总销售额": "741,837,950",
    "奖池余额": "427,210,484"
  },
  {
    "期号": "26065",
    "开奖日期": "2026-06-09",
    "红球": "07,08,16,24,30,32",
    "蓝球": "02",
    "红球号码1": "07",
    "红球号码2": "08",
    "红球号码3": "16",
    "红球号码4": "24",
    "红球号码5": "30",
    "红球号码6": "32",
    "蓝球号码1": "02",
    "总销售额": "706,837,950",
    "奖池余额": "386,314,046"
  },
  {
    "期号": "26066",
    "开奖日期": "2026-06-11",
    "红球": "05,11,21,23,24,29",
    "蓝球": "16",
    "红球号码1": "05",
    "红球号码2": "11",
    "红球号码3": "21",
    "红球号码4": "23",
    "红球号码5": "24",
    "红球号码6": "29",
    "蓝球号码1": "16",
    "总销售额": "671,837,950",
    "奖池余额": "392,786,646"
  }
]